serial_j/__init__.py
serial_j/const.py
serial_j/hp.py
serial_j-1.1.2.dist-info/LICENSE
serial_j-1.1.2.dist-info/METADATA
serial_j-1.1.2.dist-info/WHEEL
serial_j-1.1.2.dist-info/top_level.txt
serial_j-1.1.2.dist-info/RECORD
