Metadata-Version: 2.1
Name: serial-j
Version: 1.1.2
Summary: Validating and Serializing JSON data into Python object with minimal effort.
Home-page: https://github.com/JunpuFan/serial-j
Author: Junpu Fan
Author-email: junpufan@me.com 
License: MIT
Platform: UNKNOWN
Classifier: Programming Language :: Python :: 3
Classifier: License :: OSI Approved :: MIT License
Classifier: Operating System :: OS Independent
